ArgCache/__init__.py
ArgCache/ArgCache.py
argcache-0.2.2.dist-info/LICENSE
argcache-0.2.2.dist-info/METADATA
argcache-0.2.2.dist-info/WHEEL
argcache-0.2.2.dist-info/RECORD
